LICENCE
MANIFEST.in
README
README.rst
setup.py
valideer/__init__.py
valideer/base.py
valideer/compat.py
valideer/validators.py
valideer.egg-info/PKG-INFO
valideer.egg-info/SOURCES.txt
valideer.egg-info/dependency_links.txt
valideer.egg-info/requires.txt
valideer.egg-info/top_level.txt
valideer/tests/__init__.py
valideer/tests/test_validators.py