Metadata-Version: 1.1
Name: valideer
Version: 0.4.2
Summary: Lightweight data validation and adaptation library for Python
Home-page: https://github.com/podio/valideer
Author: George Sakkis
Author-email: george.sakkis@gmail.com
License: UNKNOWN
Keywords: validation adaptation typechecking jsonschema
Platform: any
Classifier: Development Status :: 5 - Production/Stable
Classifier: Intended Audience :: Developers
Classifier: Operating System :: OS Independent
Classifier: Programming Language :: Python :: 2
Classifier: Programming Language :: Python :: 2.7
Classifier: Programming Language :: Python :: 3
Classifier: Programming Language :: Python :: 3.3
Classifier: Programming Language :: Python :: 3.4
Classifier: Topic :: Software Development :: Libraries :: Python Modules
Classifier: License :: OSI Approved :: MIT License
